ykb/__init__.py
ykb/version.py
ykb/ykb.py
ykb-0.1.0.dist-info/METADATA
ykb-0.1.0.dist-info/WHEEL
ykb-0.1.0.dist-info/entry_points.txt
ykb-0.1.0.dist-info/top_level.txt
ykb-0.1.0.dist-info/RECORD
