Metadata-Version: 2.1
Name: ykb
Version: 0.1.0
Summary: Personal knowledge base that uses plain markdown files as storage backend.
Home-page: https://github.com/toolleeo/ykb
Author: Tullio Facchinetti
Author-email: toolleeo@gmail.com
License: GPL-3
Platform: UNKNOWN
Classifier: Programming Language :: Python :: 3
Classifier: Operating System :: OS Independent
Requires-Dist: Click
